{
  "header": {
    "title": "고입 자료실",
    "shortDescription": "카테고리별 핵심 자료를 빠르게 찾고, 클릭해서 상세 다이얼로그로 확인하세요.",
    "detailDescription": "이 자료실은 한국 캐리어패스 일반 루트/특수 루트 문서를 바탕으로 구성되었습니다. 목록에서는 핵심 요약만 보여주고, 상세 내용(표/체크리스트/Mermaid)은 다이얼로그에서 확인하도록 분리했습니다.",
    "totalDocuments": 20,
    "lastUpdated": "2026-04-08",
    "tip": "📌 카테고리 필터로 필요한 자료를 빠르게 찾으세요. 상세 내용은 클릭하면 열려요!"
  },
  "categories": [
    {
      "id": "admission_strategy",
      "label": "입시전략",
      "emoji": "🎯",
      "description": "루트별 입시 전략과 합격 로드맵"
    },
    {
      "id": "school_comparison",
      "label": "학교비교",
      "emoji": "📊",
      "description": "학교 유형별 특성과 차이점 비교"
    },
    {
      "id": "study_material",
      "label": "학습자료",
      "emoji": "📚",
      "description": "학년별·과목별 학습 가이드와 체크리스트"
    },
    {
      "id": "interview_prep",
      "label": "면접준비",
      "emoji": "🎤",
      "description": "학교별 면접 질문과 답변 프레임워크"
    },
    {
      "id": "mental_health",
      "label": "멘탈관리",
      "emoji": "🧘",
      "description": "번아웃 예방, 스트레스 관리, 동기부여"
    },
    {
      "id": "parent_guide",
      "label": "학부모가이드",
      "emoji": "👨‍👩‍👧",
      "description": "학부모를 위한 고입 지원 전략과 소통법"
    },
    {
      "id": "special_institutions",
      "label": "특수기관",
      "emoji": "🏫",
      "description": "특수 학교·기관 정보와 입시 전략"
    },
    {
      "id": "other",
      "label": "기타",
      "emoji": "📋",
      "description": "FAQ, 특수 상황, 기타 유용한 정보"
    }
  ],
  "documents": [
    {
      "id": "admission-strategy-general-route-map",
      "categoryId": "admission_strategy",
      "title": "일반 루트 입시 전략 맵",
      "summary": "루트 A~D(정시/학종/투트랙/지방국립) 핵심 전략 요약",
      "markdownPath": "/resource-hub/admission_strategy_general_route_map.md",
      "tags": ["일반루트", "정시", "학종", "투트랙"],
      "keyTopics": ["정시 루트 전략", "학종 루트 전략", "투트랙 병행법", "지방국립 전략"],
      "difficultyLevel": 3,
      "estimatedReadTime": "12분",
      "priority": 1
    },
    {
      "id": "admission-strategy-special-route-map",
      "categoryId": "admission_strategy",
      "title": "특수 루트 입시 전략 맵",
      "summary": "루트 E~K(과학고/사관/경찰대/로스쿨/행시/해외/의대) 정리",
      "markdownPath": "/resource-hub/admission_strategy_special_route_map.md",
      "tags": ["특수루트", "과학고", "사관학교", "의대"],
      "keyTopics": ["과학고 루트", "사관학교 루트", "의대 루트", "해외대학 루트"],
      "difficultyLevel": 4,
      "estimatedReadTime": "15분",
      "priority": 2
    },
    {
      "id": "school-comparison-general-vs-special",
      "categoryId": "school_comparison",
      "title": "일반고 vs 특목·자사 비교",
      "summary": "선발 구조, 학습 강도, 리스크를 한 표로 비교",
      "markdownPath": "/resource-hub/school_comparison_general_vs_special.md",
      "tags": ["학교비교", "일반고", "특목고", "자사고"],
      "keyTopics": ["선발 구조 비교", "학습 강도 차이", "리스크 분석", "대입 성과"],
      "difficultyLevel": 2,
      "estimatedReadTime": "8분",
      "priority": 1
    },
    {
      "id": "school-comparison-route-difficulty-reward",
      "categoryId": "school_comparison",
      "title": "루트별 난이도·보상 비교",
      "summary": "주요 루트별 준비 난이도와 10년차 보상 수준 요약",
      "markdownPath": "/resource-hub/school_comparison_route_difficulty_reward.md",
      "tags": ["난이도", "보상", "커리어", "비교표"],
      "keyTopics": ["준비 난이도", "10년차 보상", "리스크 대비 보상", "커리어 전망"],
      "difficultyLevel": 3,
      "estimatedReadTime": "10분",
      "priority": 2
    },
    {
      "id": "study-material-middle-school-checklist",
      "categoryId": "study_material",
      "title": "중학생 고입 준비 체크리스트",
      "summary": "중1~중3 학기별 점검 항목과 필수 준비물",
      "markdownPath": "/resource-hub/study_material_middle_school_checklist.md",
      "tags": ["체크리스트", "중학생", "준비"],
      "keyTopics": ["학기별 점검항목", "필수 준비물", "시간표 관리", "학원 선택"],
      "difficultyLevel": 1,
      "estimatedReadTime": "5분",
      "priority": 1
    },
    {
      "id": "study-material-grade-timeline",
      "categoryId": "study_material",
      "title": "학년별 실행 타임라인",
      "summary": "중학교~고3까지 루트 공통 실행 타임라인",
      "markdownPath": "/resource-hub/study_material_grade_timeline.md",
      "tags": ["타임라인", "학년전략", "실행계획"],
      "keyTopics": ["중학교 타임라인", "고등학교 타임라인", "루트별 일정", "핵심 마일스톤"],
      "difficultyLevel": 2,
      "estimatedReadTime": "7분",
      "priority": 1
    },
    {
      "id": "interview-prep-special-school",
      "categoryId": "interview_prep",
      "title": "특수학교 면접 대비 질문집",
      "summary": "사관학교/경찰대/영재고 면접 공통 질문과 답변 프레임",
      "markdownPath": "/resource-hub/interview_prep_special_school_questions.md",
      "tags": ["면접", "사관학교", "경찰대", "영재고"],
      "keyTopics": ["공통 면접 질문", "답변 프레임", "면접 에티켓", "합불 판단 기준"],
      "difficultyLevel": 3,
      "estimatedReadTime": "10분",
      "priority": 2
    },
    {
      "id": "interview-prep-self-intro-template",
      "categoryId": "interview_prep",
      "title": "자기소개·포트폴리오 템플릿",
      "summary": "학종/해외대/특수전형 공통 자기소개 구조",
      "markdownPath": "/resource-hub/interview_prep_self_intro_template.md",
      "tags": ["자기소개", "포트폴리오", "템플릿"],
      "keyTopics": ["자기소개 구조", "포트폴리오 작성법", "강점 어필 전략", "실수 방지 체크"],
      "difficultyLevel": 2,
      "estimatedReadTime": "8분",
      "priority": 1
    },
    {
      "id": "other-special-situation-routes",
      "categoryId": "other",
      "title": "특수 상황 루트 가이드",
      "summary": "재수/N수, 검정고시, 기회균형, 장애인 특별전형 대응 전략",
      "markdownPath": "/resource-hub/other_special_situation_routes.md",
      "tags": ["재수", "검정고시", "기회균형", "특별전형"],
      "keyTopics": ["재수/N수 전략", "검정고시 루트", "기회균형 전형", "장애인 특별전형"],
      "difficultyLevel": 3,
      "estimatedReadTime": "10분",
      "priority": 3
    },
    {
      "id": "other-faq-core-questions",
      "categoryId": "other",
      "title": "자주 묻는 질문 핵심 10선",
      "summary": "입시 재도전/장학금/지원조건 중심으로 빠른 답변",
      "markdownPath": "/resource-hub/other_faq_core_questions.md",
      "tags": ["FAQ", "질문답변", "핵심정리"],
      "keyTopics": ["입시 재도전", "장학금 안내", "지원 조건", "자주 하는 실수"],
      "difficultyLevel": 1,
      "estimatedReadTime": "5분",
      "priority": 1
    },
    {
      "id": "admission-strategy-school-type-decision-tree",
      "categoryId": "admission_strategy",
      "title": "학교 유형 선택 의사결정 트리",
      "summary": "과목 적성·성적·성격·비용을 기반으로 최적의 학교 유형을 찾는 단계별 의사결정 가이드",
      "markdownPath": "/resource-hub/admission_strategy_school_type_decision_tree.md",
      "tags": ["의사결정", "학교선택", "적성", "가이드"],
      "keyTopics": ["과목별 적성 분석", "성격 유형별 학교 매칭", "비용 대비 효과 분석", "리스크 평가"],
      "difficultyLevel": 2,
      "estimatedReadTime": "8분",
      "priority": 1
    },
    {
      "id": "admission-strategy-2028-admission-trend",
      "categoryId": "admission_strategy",
      "title": "2028학년도 입시 트렌드 분석",
      "summary": "정시 확대, 학종 변화, IB 도입 확대 등 최신 입시 환경 변화 정리",
      "markdownPath": "/resource-hub/admission_strategy_2028_admission_trend.md",
      "tags": ["2028입시", "트렌드", "정시확대", "학종변화"],
      "keyTopics": ["정시 비율 확대 영향", "학종 평가 기준 변화", "IB 학교 확대 현황", "대학별 전형 변화"],
      "difficultyLevel": 3,
      "estimatedReadTime": "10분",
      "priority": 2
    },
    {
      "id": "school-comparison-ib-vs-regular",
      "categoryId": "school_comparison",
      "title": "IB 학교 vs 일반 교육과정 비교",
      "summary": "IB 디플로마와 일반 교육과정의 학습 방식·평가·대학 진학 차이 상세 비교",
      "markdownPath": "/resource-hub/school_comparison_ib_vs_regular.md",
      "tags": ["IB", "교육과정", "비교", "해외대학"],
      "keyTopics": ["IB 과목 구성과 평가 방식", "TOK·CAS·EE 이해", "국내·해외 대학 진학률", "IB 적합 성격 유형"],
      "difficultyLevel": 3,
      "estimatedReadTime": "12분",
      "priority": 2
    },
    {
      "id": "study-material-subject-study-guide",
      "categoryId": "study_material",
      "title": "과목별 효율적 공부법 가이드",
      "summary": "수학·과학·영어·국어 각 과목의 학습 전략과 추천 교재·인강 정리",
      "markdownPath": "/resource-hub/study_material_subject_study_guide.md",
      "tags": ["공부법", "과목별", "학습전략", "교재추천"],
      "keyTopics": ["수학 문제풀이 전략", "과학 개념 정리법", "영어 독해·어휘 전략", "국어 비문학·문학 접근법"],
      "difficultyLevel": 2,
      "estimatedReadTime": "15분",
      "priority": 1
    },
    {
      "id": "study-material-self-directed-learning",
      "categoryId": "study_material",
      "title": "자기주도 학습 설계 가이드",
      "summary": "학습 계획 수립, 시간 관리, 집중력 향상을 위한 실전 가이드",
      "markdownPath": "/resource-hub/study_material_self_directed_learning.md",
      "tags": ["자기주도학습", "시간관리", "집중력", "계획수립"],
      "keyTopics": ["주간·일간 학습 플래너 작성법", "포모도로 기법 활용", "집중력 방해 요소 제거", "복습 주기 최적화"],
      "difficultyLevel": 1,
      "estimatedReadTime": "8분",
      "priority": 1
    },
    {
      "id": "interview-prep-common-mistakes",
      "categoryId": "interview_prep",
      "title": "면접 실수 TOP 10과 대처법",
      "summary": "고입·대입 면접에서 자주 하는 실수와 합격생이 알려주는 대처 전략",
      "markdownPath": "/resource-hub/interview_prep_common_mistakes.md",
      "tags": ["면접실수", "대처법", "합격전략", "면접팁"],
      "keyTopics": ["긴장 관리법", "모르는 질문 대처", "자기소개 구조화", "후속 질문 대비"],
      "difficultyLevel": 2,
      "estimatedReadTime": "7분",
      "priority": 2
    },
    {
      "id": "mental-health-burnout-prevention",
      "categoryId": "mental_health",
      "title": "번아웃 예방 & 회복 가이드",
      "summary": "고입 준비 과정에서의 번아웃 초기 징후 인식, 예방법, 회복 전략",
      "markdownPath": "/resource-hub/mental_health_burnout_prevention.md",
      "tags": ["번아웃", "멘탈관리", "회복", "예방"],
      "keyTopics": ["번아웃 자가진단 체크리스트", "수면·운동·영양 관리", "스트레스 해소법 5가지", "도움 요청하는 법"],
      "difficultyLevel": 1,
      "estimatedReadTime": "6분",
      "priority": 1
    },
    {
      "id": "mental-health-exam-anxiety",
      "categoryId": "mental_health",
      "title": "시험 불안 극복 실전 매뉴얼",
      "summary": "시험 전·중·후 불안 관리 기법과 집중력 회복 전략",
      "markdownPath": "/resource-hub/mental_health_exam_anxiety.md",
      "tags": ["시험불안", "긴장관리", "집중력", "호흡법"],
      "keyTopics": ["4-7-8 호흡법", "시험 전 루틴 만들기", "시험 중 패닉 대처법", "시험 후 감정 정리"],
      "difficultyLevel": 1,
      "estimatedReadTime": "5분",
      "priority": 1
    },
    {
      "id": "parent-guide-support-strategy",
      "categoryId": "parent_guide",
      "title": "학부모 고입 지원 전략 가이드",
      "summary": "자녀의 고입 과정에서 학부모가 할 수 있는 효과적 지원 방법과 소통 전략",
      "markdownPath": "/resource-hub/parent_guide_support_strategy.md",
      "tags": ["학부모", "지원전략", "소통", "멘탈케어"],
      "keyTopics": ["자녀 적성 파악 돕기", "압박 없는 동기부여", "성적 하락 시 대화법", "학교 선택 함께하기"],
      "difficultyLevel": 1,
      "estimatedReadTime": "8분",
      "priority": 2
    },
    {
      "id": "parent-guide-financial-planning",
      "categoryId": "parent_guide",
      "title": "고입·대입 교육비 재정 계획",
      "summary": "학교 유형별 교육비, 장학금, 학자금 대출 등 재정 계획 수립 가이드",
      "markdownPath": "/resource-hub/parent_guide_financial_planning.md",
      "tags": ["교육비", "장학금", "재정계획", "학자금"],
      "keyTopics": ["학교 유형별 3년 교육비", "장학금 종류와 신청법", "교육비 절감 전략", "학자금 대출 안내"],
      "difficultyLevel": 2,
      "estimatedReadTime": "10분",
      "priority": 3
    }
  ]
}
