{
  "intro": {
    "emoji": "📚",
    "title": "활동 전체 목록 — 알아두면 좋은 곳",
    "description": "아래는 실제로 참여할 수 있는 봉사·캠프·수상(대회)·전시회 공식 채널이에요. ==항목을 누르면 일정·자격·규모·이전 작품 예시 등 자세한 설명 팝업==이 떠요. 모집 일정·비용은 매년 바뀌니 반드시 공식 홈페이지에서 최종 확인하세요."
  },
  "groups": [
    {
      "id": "award",
      "label": "수상 · 대회",
      "emoji": "🏆",
      "color": "#F472B6",
      "items": [
        {
          "name": "한국수학올림피아드 (KMO)",
          "org": "대한수학회",
          "grades": "중·고",
          "url": "https://www.kms.or.kr",
          "note": "수학 최고 권위 경시",
          "detail": {
            "summary": "수학 분야 최고 권위의 경시대회예요. 의대·이공계 최상위권의 대표 스펙으로, ==1차 합격만으로도 강력한 증거==가 됩니다.",
            "schedule": [
              { "label": "🗓️ 1차 시험", "value": "매년 8월경 (전국 동시 시행)" },
              { "label": "🗓️ 2차 시험", "value": "매년 11월경 (1차 통과자 대상)" },
              { "label": "📝 접수", "value": "시험 2~3개월 전 (공식 홈페이지 공지)" }
            ],
            "eligibility": [
              "중등부 (중학생) / 고등부 (고등학생) 별도 운영",
              "국적·학교 제한 없이 전국 누구나 응시 가능",
              "최종 입상자는 국제수학올림피아드(IMO) 국가대표 선발 대상"
            ],
            "scale": [
              "전국 단위 대규모 시험 — 응시자 수만 명",
              "1차(객관식·단답형) → 2차(서술형) → 최종 선발",
              "IMO 대표 선발까지 총 3~4단계"
            ],
            "pastWorks": [
              "대수·기하·정수론·조합론 4개 분야에서 출제",
              "역대 수상자 다수가 서울대·KAIST·포스텍 수시 최상위 합격",
              "2차 수상자(동상 이상)는 대입 면접에서 직접 언급 가능"
            ],
            "cost": "응시료 있음 (공식 홈페이지 확인)",
            "tips": [
              "교외 수상이라 생기부 기재 불가지만 ==준비 과정을 수학 세특에 녹이면 강력한 증거==가 돼요.",
              "기출문제는 대한수학회 홈페이지에서 무료 제공합니다."
            ]
          }
        },
        {
          "name": "한국생물올림피아드 (KBO)",
          "org": "한국생물올림피아드위원회",
          "grades": "중·고",
          "url": "https://kbo.bioedu.kr",
          "note": "의약·생명 지망 필수",
          "detail": {
            "summary": "의약·생명공학·수의학 지망생의 대표 활동이에요. ==중학생 전용 mskbo.bioedu.kr==도 별도 운영합니다.",
            "schedule": [
              { "label": "🗓️ 1차 시험", "value": "매년 4~5월경" },
              { "label": "🗓️ 2차 시험", "value": "매년 6~7월경 (1차 통과자)" },
              { "label": "🏅 최종 선발", "value": "매년 8월경 (국제대회 대표)" }
            ],
            "eligibility": [
              "중학생 부문 (MSKBO) / 고등학생 부문 (KBO) 분리 운영",
              "전국 누구나 응시 가능 (학교 추천 불필요)",
              "최종 수상자 — 국제생물올림피아드(IBO) 대표 선발 대상"
            ],
            "scale": [
              "전국 단위 / 연간 수천 명 응시",
              "세포학·유전학·생태학·진화 등 고교 생물 전 범위",
              "1차 필기 → 2차 실험 실기 → 최종"
            ],
            "pastWorks": [
              "최종 수상자 다수가 의대·수의대·약대 수시 합격",
              "실험 실기 영역: 현미경 관찰·DNA 전기영동·효소 반응 실험 등",
              "국제 IBO 금·은·동메달 수상 시 세계적 수준 증명"
            ],
            "tips": [
              "==생물 세특 + KBO 준비를 연결==하면 의대·수의대 면접에서 설득력이 크게 높아져요.",
              "중학생은 MSKBO(https://mskbo.bioedu.kr)로 먼저 도전해보세요."
            ]
          }
        },
        {
          "name": "한국정보올림피아드 (KOI)",
          "org": "과기정통부",
          "grades": "초·중·고",
          "url": "https://www.koi.or.kr",
          "note": "알고리즘·프로그래밍",
          "detail": {
            "summary": "알고리즘·프로그래밍 실력을 겨루는 대회로, AI·SW·컴퓨터공학 지망생의 ==대표 스펙 중 하나==예요.",
            "schedule": [
              { "label": "🗓️ 1차 대회", "value": "매년 6월경 (온라인 예선)" },
              { "label": "🗓️ 2차 대회", "value": "매년 7~8월경 (오프라인 본선)" },
              { "label": "📝 접수", "value": "5월경 (공식 홈페이지 공지)" }
            ],
            "eligibility": [
              "초등부·중등부·고등부 3개 부문",
              "전국 누구나 응시 가능, 학교 추천 불필요",
              "최종 입상자 — 국제정보올림피아드(IOI) 대표 선발"
            ],
            "scale": [
              "전국 수만 명 응시 / 부문별 입상자 선발",
              "C/C++·Java·Python 사용 가능",
              "자료구조·그래프·DP·수학적 사고 종합 출제"
            ],
            "pastWorks": [
              "역대 금상 수상자 다수 — 서울대 컴공·KAIST 전산 조기합격",
              "2차 동상 이상 수상자도 SW 특기자 전형에서 강력한 증거",
              "준비 과정에서 백준(acmicpc.net) 1000문제 이상 풀이가 일반적"
            ],
            "cost": "응시료 있음 (소액, 공식 홈페이지 확인)",
            "tips": [
              "==백준(https://www.acmicpc.net)으로 먼저 기초를 쌓고== 도전하세요.",
              "1차 통과만으로도 교내 동아리·세특 활동 소재로 충분히 활용 가능해요."
            ]
          }
        },
        {
          "name": "전국학생과학발명품경진대회",
          "org": "한국발명진흥회",
          "grades": "초·중·고",
          "url": "https://www.kipa.org",
          "note": "발명·아이디어",
          "detail": {
            "summary": "학생들의 창의적 발명품을 겨루는 전국 대표 발명 대회예요. ==생활 속 문제를 해결하는 아이디어==가 핵심입니다.",
            "schedule": [
              { "label": "🗓️ 시·도 예선", "value": "매년 봄~여름 (3~6월경)" },
              { "label": "🗓️ 전국 대회", "value": "매년 7~9월경" },
              { "label": "📝 접수", "value": "시·도 교육청 통해 접수" }
            ],
            "eligibility": [
              "초·중·고등학생 부문별 출품",
              "개인 또는 2인 이하 팀 출품",
              "학교 추천 → 시·도 예선 → 전국 대회 단계 진행"
            ],
            "scale": [
              "전국 단위 / 시·도 예선 후 본선 진출",
              "8개 분야: 기계·전기전자·화학·생물·농림수산·의약보건·생활·기타",
              "대통령상·국무총리상·장관상 등 시상"
            ],
            "pastWorks": [
              "예시 수상작: '시각장애인을 위한 촉각 지도 장치' (전기전자 부문)",
              "예시 수상작: '음식물 쓰레기 압축 자동 분리기' (생활 부문)",
              "예시 수상작: '스마트 약 복용 알림 케이스' (의약보건 부문)",
              "예시 수상작: '재활용 가능한 생분해 포장재 발명' (화학 부문)"
            ],
            "tips": [
              "==교내 탐구 과정과 연결==하면 발명 → 세특 → 면접 소재로 이어지는 강력한 스토리가 만들어져요.",
              "완성도보다 '왜 만들었는지' 문제 정의가 더 중요하게 평가됩니다."
            ]
          }
        },
        {
          "name": "전국 학생 코딩경진대회",
          "org": "코딩경진대회 조직위",
          "grades": "초·중·고",
          "url": "https://codingcontest.or.kr",
          "note": "블록·파이썬·AI 코딩",
          "detail": {
            "summary": "블록코딩·파이썬·AI 코딩 등 부문별로 겨루는 전국 학생 코딩 대회예요. (삼성 주니어 SW 창작대회는 최근 개최 소식이 없어 본 대회로 안내합니다.)",
            "schedule": [
              { "label": "📝 접수·예선", "value": "공식 홈페이지 공지 확인" }
            ],
            "eligibility": [
              "초·중·고등학생 부문별 참가",
              "블록코딩·AI코딩·파이썬·교과연계 AI/SW 탐구 부문"
            ],
            "scale": ["전국 단위 / 부문별 시상"],
            "pastWorks": [
              "예시: 생활 속 문제를 해결하는 블록코딩 게임·앱",
              "예시: 파이썬 데이터 분석·자동화 프로젝트"
            ],
            "tips": [
              "==SW·컴공 지망생은 KOI·백준과 함께== 도전하면 시너지가 커요.",
              "삼성 주니어 SW 창작대회는 2020년 이후 개최 정보가 확인되지 않아 제외했어요."
            ]
          }
        },
        {
          "name": "백준 온라인 저지 (알고리즘)",
          "org": "Baekjoon",
          "grades": "중·고",
          "url": "https://www.acmicpc.net",
          "note": "코딩 실력 훈련·대회",
          "detail": {
            "summary": "국내 최대 알고리즘 문제풀이 플랫폼이에요. 상시 연습과 정기 오픈콘테스트에 참여할 수 있어요.",
            "schedule": [
              { "label": "🗓️ 문제풀이", "value": "상시 (24시간 자동 채점)" },
              { "label": "🗓️ 대회", "value": "오픈콘테스트 수시 개최 (사이트 공지)" }
            ],
            "eligibility": [
              "누구나 무료 가입·이용",
              "실버·골드·플래티넘·다이아 등 티어(랭킹) 시스템"
            ],
            "scale": [
              "30만 문제 이상 보유 / 국내 최다",
              "KOI·ICPC 대비 핵심 훈련 플랫폼"
            ],
            "pastWorks": [
              "플래티넘 이상 달성자 — 서울대 컴공·KAIST SW 트랙 지원 시 강력한 증거",
              "골드 달성 후 KOI 1차 통과 비율 높음",
              "세특에 '문제 풀이 사고 과정·오류 수정 경험'으로 기록 가능"
            ],
            "tips": [
              "==목표 티어(골드 이상)를 정하고 단계별로 올라가세요.==",
              "대회 참여 기록보다 '특정 알고리즘 개념을 탐구한 과정'을 세특에 녹이는 것이 입시에 더 유리해요."
            ]
          }
        },
        {
          "name": "대한민국디자인전람회",
          "org": "한국디자인진흥원",
          "grades": "초·중·고~",
          "url": "https://award.kidp.or.kr",
          "note": "디자인 공모",
          "detail": {
            "summary": "산업통상자원부 주최의 국내 최고 권위 디자인 공모전이에요. 청소년 부문이 있어 학생도 도전 가능합니다.",
            "schedule": [
              { "label": "📝 접수", "value": "매년 하반기 (공식 홈페이지 확인)" },
              { "label": "🗓️ 시상식", "value": "매년 연말 (서울)" }
            ],
            "eligibility": [
              "청소년 부문 (초·중·고등학생) 별도 운영",
              "제품·시각·공간·서비스디자인 등 분야별 출품",
              "개인 또는 팀 출품 가능"
            ],
            "scale": [
              "60회 이상 이어진 전통 있는 국내 최고 권위 공모전",
              "대통령상·국무총리상·장관상 등 시상"
            ],
            "pastWorks": [
              "청소년 수상작 예시: '노인 낙상 방지 미끄럼 방지 신발 솔 디자인'",
              "청소년 수상작 예시: '시각장애인용 촉각 지하철 노선도'",
              "청소년 수상작 예시: '재활용 재료로 만든 어린이 교육 완구'"
            ],
            "tips": [
              "==사회적 가치와 사용자 경험을 고려한 디자인==이 평가에서 우위예요.",
              "디자인 계열(시각디자인·산업디자인·UX) 지망생에게 강력한 포트폴리오가 됩니다."
            ]
          }
        }
      ]
    },
    {
      "id": "camp",
      "label": "캠프",
      "emoji": "🏕️",
      "color": "#FBBF24",
      "items": [
        {
          "name": "과학영재교육원 (대학 부설)",
          "org": "한국과학창의재단",
          "grades": "초·중",
          "url": "https://www.kosac.re.kr",
          "note": "심화 과학교육",
          "detail": {
            "summary": "전국 주요 대학 부설 영재교육원에서 심화 과학·수학 교육을 1년 과정으로 받는 프로그램이에요.",
            "schedule": [
              { "label": "📝 모집", "value": "보통 전년도 11~12월 (학교 추천 + 선발)" },
              { "label": "🗓️ 운영", "value": "3월 ~ 다음해 2월 (1년 과정)" }
            ],
            "eligibility": [
              "초·중학생 (각 대학 부설별 모집 학년 상이)",
              "학교장 추천 → 서류·면접·지필 선발",
              "서울대·KAIST·포스텍·지방거점대학 등 전국 운영"
            ],
            "scale": [
              "전국 수십 개 대학 부설 운영",
              "매주 토요일 또는 방학 집중 과정",
              "교수·연구원 직접 지도"
            ],
            "pastWorks": [
              "수료 후 과학고·영재학교 진학률이 높음",
              "세특에 '영재교육원 탐구 과제 수행' 기록 가능",
              "R&E(대학 연계 연구) 프로그램으로 이어지는 경우 많음"
            ],
            "cost": "무료~10만원 수준 (기관별 상이)",
            "tips": ["==고입 과학고·영재학교 준비생에게 거의 필수==적인 활동으로 인식돼요."]
          }
        },
        {
          "name": "KAIST 과학영재캠프",
          "org": "KAIST",
          "grades": "중·고",
          "url": "https://gifted.kaist.ac.kr",
          "note": "여름·겨울 캠프",
          "detail": {
            "summary": "KAIST 과학영재교육연구원이 운영하는 여름·겨울 집중 과학 영재 캠프예요.",
            "schedule": [
              { "label": "🗓️ 여름 캠프", "value": "매년 7~8월 (약 1주 집중)" },
              { "label": "🗓️ 겨울 캠프", "value": "매년 12~1월 (약 1주 집중)" },
              { "label": "📝 모집", "value": "캠프 2~3개월 전 (홈페이지 공지)" }
            ],
            "eligibility": [
              "중·고등학생 (모집 요강별 학년 제한 상이)",
              "서류 심사 후 선발 (자기소개·탐구 계획서 등)"
            ],
            "scale": [
              "KAIST 캠퍼스(대전) 현장 진행",
              "KAIST 교수·연구원 강의·실험 직접 참여"
            ],
            "pastWorks": [
              "캠프 중 직접 실험·프로젝트 수행 → 보고서 제출",
              "물리·화학·생물·수학·정보 분야별 심화 탐구",
              "수료자 다수가 과학고·영재학교·이공계 대학 진학"
            ],
            "cost": "무료~10만원 수준",
            "tips": ["캠프에서 수행한 ==탐구 보고서를 세특 소재==로 연결하면 강력한 전공적합성 증거가 돼요."]
          }
        },
        {
          "name": "삼성 드림클래스 코딩 캠프",
          "org": "삼성전자",
          "grades": "중",
          "url": "https://www.dreamclass.samsung.com",
          "note": "무료 코딩",
          "detail": {
            "summary": "삼성전자가 운영하는 중학생 대상 무료 코딩·SW 교육 캠프예요.",
            "schedule": [{ "label": "🗓️ 운영", "value": "방학 중 (여름·겨울, 홈페이지 공지)" }],
            "eligibility": ["중학생 중심 (요강별 대상 확인)", "무상 제공 (교통비·숙식 일부 지원)"],
            "scale": ["전국 각 지역 거점 대학에서 진행", "삼성전자 임직원·대학생 강사 진행"],
            "pastWorks": [
              "스크래치·파이썬·앱 인벤터 기초 코딩 실습",
              "수료 후 팀 프로젝트 발표"
            ],
            "cost": "무료",
            "tips": ["수료 후 ==전국 학생 코딩경진대회·정보올림피아드(KOI) 도전으로 자연스럽게 이어==갈 수 있어요."]
          }
        },
        {
          "name": "국립생태원 청소년 생태캠프",
          "org": "환경부·국립생태원",
          "grades": "중·고",
          "url": "https://www.nie.re.kr",
          "note": "생태·환경",
          "detail": {
            "summary": "국립생태원(충남 서천)에서 진행하는 생태·환경 체험 캠프예요.",
            "schedule": [{ "label": "🗓️ 운영", "value": "방학 중 (공식 홈페이지 확인)" }],
            "eligibility": ["중·고등학생 (요강별 인원 제한)"],
            "scale": ["에코리움(세계 5대 기후대 전시관) 내 체험", "생태연구원 동행 현장 탐사"],
            "pastWorks": [
              "멸종위기종 관찰·보전 실습",
              "생태 탐구 보고서 작성 → 환경·생명 세특 연계"
            ],
            "cost": "3~5만원 수준",
            "tips": ["환경·생물·수의 계열 지망생의 ==탐구 동기 형성에 최적화==된 캠프예요."]
          }
        },
        {
          "name": "SW마에스트로",
          "org": "과기정통부·IITP",
          "grades": "고3~",
          "url": "https://www.swmaestro.ai",
          "note": "지원금+심화 SW",
          "detail": {
            "summary": "정부 지원 최정예 SW 인재 양성 과정이에요. ==연수비·프로젝트 지원금==이 제공되고 수료 시 증서가 발급됩니다.",
            "schedule": [
              { "label": "📝 모집", "value": "매년 연초~봄 (공식 홈페이지 확인)" },
              { "label": "🗓️ 운영", "value": "연중 (1년 과정)" }
            ],
            "eligibility": [
              "고3 졸업예정자·대학생·일반인 (요강별 상이)",
              "서류·코딩테스트·면접 전형"
            ],
            "scale": [
              "매년 100~200명 선발",
              "팀 프로젝트 중심 (멘토 전문가 1:1 지도)"
            ],
            "pastWorks": [
              "수료 프로젝트 예시: AI 기반 의료 영상 분석 플랫폼",
              "수료 프로젝트 예시: 실시간 대중교통 혼잡도 예측 서비스",
              "수료 프로젝트 예시: 장애인 보조 스마트 글러브"
            ],
            "cost": "무료 + 연수 지원금 (월별 지급)",
            "tips": ["대학 합격 후 1학년 재학 중 도전하는 경우가 많아요. 고3은 ==졸업예정자 자격으로 지원== 가능해요."]
          }
        },
        {
          "name": "유네스코 청소년 미디어 캠프",
          "org": "유네스코한국위원회",
          "grades": "고",
          "url": "https://www.unesco.or.kr",
          "note": "미디어·국제",
          "detail": {
            "summary": "미디어 리터러시와 국제 이해를 키우는 청소년 캠프예요. 외교·국제 관계·언론 계열 지망생에게 특히 유용해요.",
            "schedule": [{ "label": "🗓️ 운영", "value": "방학 중 (공식 홈페이지 확인)" }],
            "eligibility": ["고등학생 중심 (요강별 상이)"],
            "scale": ["국제 미디어 제작 실습", "외국 학생과의 공동 프로젝트 (영어 사용)"],
            "cost": "무료~10만원 수준",
            "tips": ["캠프 중 제작한 ==영상·기사를 포트폴리오==로 남겨두세요."]
          }
        }
      ]
    },
    {
      "id": "volunteer",
      "label": "봉사활동",
      "emoji": "🤝",
      "color": "#60A5FA",
      "items": [
        {
          "name": "1365 자원봉사포털",
          "org": "행정안전부",
          "grades": "전학년",
          "url": "https://www.1365.go.kr",
          "note": "봉사 검색·실적확인서",
          "detail": {
            "summary": "행정안전부가 운영하는 전국 자원봉사 통합 포털이에요. 봉사처 검색·신청·실적확인서 발급을 한 곳에서 할 수 있어요.",
            "schedule": [{ "label": "🗓️ 이용", "value": "상시 (연중 봉사 모집·인증)" }],
            "eligibility": [
              "누구나 무료 가입 및 이용",
              "만 14세 미만은 보호자 동반 필요한 경우 있음",
              "청소년 봉사시간 학교·진학 서류 인증 가능"
            ],
            "scale": ["전국 수십만 봉사처 연결", "실적확인서 온라인 즉시 발급"],
            "pastWorks": [
              "인기 봉사 유형: 교육 멘토링·복지관 돌봄·환경정화·동물보호",
              "누적 300시간+ → 청소년 자원봉사 대상 신청 가능 (행정안전부)"
            ],
            "cost": "무료",
            "tips": [
              "==1회성 단순 봉사보다 같은 곳에서 정기 봉사==하는 것이 생기부에 훨씬 강하게 남아요.",
              "봉사처의 '담당자 확인' 도장이 있어야 실적확인서가 유효합니다."
            ]
          }
        },
        {
          "name": "VMS 사회복지자원봉사",
          "org": "한국사회복지협의회",
          "grades": "전학년",
          "url": "https://www.vms.or.kr",
          "note": "복지 봉사 인증",
          "detail": {
            "summary": "사회복지 분야 봉사활동 전문 포털이에요. 복지관·요양원·장애인시설 봉사에 특화돼 있어요.",
            "schedule": [{ "label": "🗓️ 이용", "value": "상시" }],
            "eligibility": ["누구나 무료 가입·이용"],
            "scale": ["전국 복지관·요양원·장애인시설 연결"],
            "pastWorks": [
              "인기 봉사: 요양원 어르신 말벗·급식 도우미, 장애인 체험 보조",
              "사회복지사·간호사·의사 지망생의 진로 탐색에 최적화"
            ],
            "cost": "무료",
            "tips": ["복지 봉사 경험을 ==진로와 연결된 에피소드==로 면접에서 구체적으로 말할 수 있어야 해요."]
          }
        },
        {
          "name": "e청소년 DOVOL",
          "org": "여성가족부",
          "grades": "전학년",
          "url": "https://www.youth.go.kr",
          "note": "청소년 봉사·활동",
          "detail": {
            "summary": "청소년활동정보서비스(e청소년)로, 청소년 자원봉사(DOVOL)와 다양한 청소년 수련 활동을 안내해요.",
            "schedule": [{ "label": "🗓️ 이용", "value": "상시" }],
            "eligibility": ["청소년 (만 9세~24세) 누구나", "학교 연계 단체 봉사 신청 가능"],
            "scale": ["전국 청소년 수련관·문화의 집 연결", "봉사·동아리·체험활동 통합 관리"],
            "cost": "무료",
            "tips": ["==DOVOL 봉사 이력이 1365와 연동==되므로 한 곳에서 관리할 수 있어요."]
          }
        }
      ]
    },
    {
      "id": "exhibition",
      "label": "전시회 · 메이커",
      "emoji": "🎨",
      "color": "#A78BFA",
      "items": [
        {
          "name": "메이커 페어 서울 (Maker Faire Seoul)",
          "org": "메이커 페어 서울 조직위",
          "grades": "전연령",
          "url": "https://www.makerfaireseoul.com/",
          "note": "자작 발명품 전시·체험 축제",
          "detail": {
            "summary": "==상상을 현실로 만드는 메이킹의 축제==! 메이커들이 직접 만든 작품을 전시·공유·체험하는 국내 대표 메이커 행사예요. 2014년 시작해 2024년 10회를 맞이했어요.",
            "schedule": [
              { "label": "🗓️ 2025 개최일", "value": "9월 27일(토)~28일(일) · 10:30~17:30" },
              { "label": "📝 메이커 모집", "value": "2025년 6월 15일(일)~7월 20일(일) · 36일간" },
              { "label": "🔎 선정 심사", "value": "7월 21일(월)~23일(수)" },
              { "label": "📢 선정 발표", "value": "7월 25일(금)" },
              { "label": "✅ 참가 등록 확인", "value": "7월 25일(금)~8월 22일(금)" },
              { "label": "📌 2026년 일정", "value": "공식 홈페이지(makerfaireseoul.com)에서 확인" }
            ],
            "eligibility": [
              "메이커 부문: 일반(개인·그룹)·커머셜·기업 부문 — 누구나 출품 신청",
              "청소년 발명 분야도 별도 운영 (학생 출품 환영)",
              "관람: 어린이~성인 누구나 · 무료 입장"
            ],
            "scale": [
              "2025 기준 — 참가 메이커 약 93팀 / 전시 8개 분야",
              "8개 분야: AI · 공예 · 로봇 · 일상 아이디어 · 적정기술·ESG · 청소년 발명 · 탐사탐험 · 태양광·DIY 모빌리티",
              "2024(10회) — 약 80부스 / DDP(동대문디자인플라자) 개최",
              "2023(9회) — 서울시립과학관 개최",
              "2019(8회) — 메이커 700명+ / 프로젝트 150개+ / 관람객 16,000명+"
            ],
            "pastWorks": [
              "🤖 AI·로봇: 'AI 기반 자율주행 미니카(라즈베리파이+카메라)', '개인용 비서 로봇', 'OpenCV 얼굴인식 출석 시스템'",
              "🌱 ESG·환경: '멸종위기동물 보호 예술 작품', '음식물 쓰레기 퇴비화 자동 기계'",
              "🎨 공예·예술: '한국 전통무늬를 담은 3륜 자동차', '우주탐사 주제 미디어아트(스페이스 챌린지)'",
              "🔧 DIY·생활: '집에서 만드는 태양광 충전 스테이션', '목공 + 아두이노 인터랙티브 가구'",
              "🧒 청소년 발명: '재활용 재료로 만든 의족 보조 기구', '아두이노 스마트 화분 자동물주기'"
            ],
            "programs": [
              "공기대포 실험실 · 소마트로프 체험",
              "리싸이클 변신합체 워크숍 (1일 3회)",
              "불꽃 납땜 스테이션 (성인 대상, 5,000원)",
              "오토마타 · 3D프린터 · 휴머노이드 로봇 무료 체험",
              "영메이커 프로젝트: 어린이 대상 공작 워크숍"
            ],
            "cost": "관람 무료 · 일부 체험 소액 유료",
            "tips": [
              "==청소년 발명 분야에 직접 출품==하면 자기주도성·창의융합의 가장 강력한 증거가 돼요.",
              "제작 과정(버전1→2 개선)을 사진·영상으로 기록해두면 세특·포트폴리오 소재로 활용 가능해요.",
              "관람만 해도 다양한 메이커를 만나고 아이디어를 얻는 좋은 경험이 됩니다."
            ]
          }
        },
        {
          "name": "전국과학전람회",
          "org": "국립중앙과학관",
          "grades": "초·중·고",
          "url": "https://www.science.go.kr",
          "note": "과학 탐구작품 전시",
          "detail": {
            "summary": "1949년에 시작한 국내 최장 역사의 과학 탐구작품 전시회예요. 2025년 제71회가 개최됩니다.",
            "schedule": [
              { "label": "🗓️ 시·도 예선", "value": "매년 봄~여름" },
              { "label": "🗓️ 전국 본선", "value": "매년 7~9월 (대전 국립중앙과학관)" },
              { "label": "📝 접수", "value": "학교·시도 교육청 통해 접수" }
            ],
            "eligibility": [
              "초·중·고등학생 부문 및 교원 부문",
              "개인 또는 2인 이하 팀 출품",
              "학교 추천 → 시·도 예선 → 전국 본선"
            ],
            "scale": [
              "전국 단위 / 시·도 예선 후 본선 약 200~300점 진출",
              "대통령상·국무총리상·교육부장관상 등 시상"
            ],
            "pastWorks": [
              "예시 수상작: '미세먼지 농도에 따른 식물 기공 변화 탐구' (생물 부문)",
              "예시 수상작: 'AI를 이용한 조류 울음소리 종 분류' (정보 부문)",
              "예시 수상작: '폐플라스틱을 활용한 친환경 단열재 제조 연구' (화학 부문)",
              "예시 수상작: '교내 태양광 발전 최적 각도 탐구' (물리 부문)"
            ],
            "tips": [
              "==단순 실험보다 '가설-검증-한계-개선' 구조==가 있는 탐구가 입상 가능성이 높아요.",
              "전국 본선 진출 시 세특에 '국립중앙과학관 전시' 경험으로 기록 가능해요."
            ]
          }
        },
        {
          "name": "대한민국 학생발명전시회",
          "org": "한국발명진흥회",
          "grades": "초·중·고",
          "url": "https://www.kipa.org",
          "note": "학생 발명품 전시·시상",
          "detail": {
            "summary": "학생들의 발명품을 전국 규모로 전시·시상하는 행사예요.",
            "schedule": [
              { "label": "🗓️ 접수·전시", "value": "매년 하반기 (공식 홈페이지 확인)" }
            ],
            "eligibility": ["초·중·고등학생 부문별 출품"],
            "scale": ["전국 단위 / 대통령상 등 고위 시상"],
            "pastWorks": [
              "예시 수상작: '스마트 안전 헬멧 (낙상 감지 센서 내장)'",
              "예시 수상작: '시각장애인용 스마트 흰 지팡이'"
            ],
            "tips": ["==전국학생과학발명품경진대회와 함께== 도전하면 중복 활용이 가능해요."]
          }
        },
        {
          "name": "대한민국 과학축제",
          "org": "과기정통부",
          "grades": "전연령",
          "url": "https://www.scienceall.com",
          "note": "과학 체험·부스 (4월)",
          "detail": {
            "summary": "매년 4월 대전 도심에서 열리는 전국 규모 과학 체험 축제예요.",
            "schedule": [
              { "label": "🗓️ 개최", "value": "매년 4월경 (대전 도심 일원, 약 5일간)" }
            ],
            "eligibility": ["누구나 관람 가능"],
            "scale": ["수십만 명 방문 / 수백 개 체험 부스", "학생 발명·탐구 전시 참여 기회 있음"],
            "cost": "무료",
            "tips": ["직접 ==탐구 부스를 운영하는 학생 발표 프로그램==도 있어요. 홈페이지 공지 확인하세요."]
          }
        },
        {
          "name": "한국만화영상진흥원 (웹툰·만화공모)",
          "org": "한국만화영상진흥원",
          "grades": "중·고",
          "url": "https://www.komacon.kr",
          "note": "만화·웹툰 전시·공모",
          "detail": {
            "summary": "만화·웹툰 전시와 학생 공모전, 웹툰 캠프 등을 운영하는 국가 기관이에요.",
            "schedule": [
              { "label": "🗓️ 전국학생만화공모전", "value": "매년 하반기 접수 (공식 홈페이지 확인)" },
              { "label": "🗓️ 웹툰 캠프", "value": "방학 중 (홈페이지 공지)" }
            ],
            "eligibility": ["중·고등학생 (공모전별 요강 확인)", "만화·웹툰·애니메이션 계열 지망생 적합"],
            "pastWorks": [
              "전국학생만화공모전 수상작 다수가 온라인·오프라인 전시",
              "수상작 예시: 사회 이슈(환경·차별·가족)를 주제로 한 단편 웹툰"
            ],
            "tips": [
              "==그림 실력보다 스토리와 메시지==가 평가의 핵심이에요.",
              "수상작은 한국만화영상진흥원 홈페이지 아카이브에서 열람 가능해요."
            ]
          }
        }
      ]
    },
    {
      "id": "international",
      "label": "국제 대회 · 로봇 · 해커톤",
      "emoji": "🌍",
      "color": "#34D399",
      "items": [
        {
          "name": "FIRST LEGO League (FLL) 한국대회",
          "org": "사단법인 상상 (FIRST·LEGO)",
          "grades": "초·중·고",
          "url": "https://firstlegoleague.or.kr/",
          "note": "세계 최대 청소년 로봇 챌린지",
          "detail": {
            "summary": "1998년 미국 FIRST 재단과 덴마크 LEGO Education이 만든 ==세계 최대 청소년 로봇 챌린지==예요. 매 시즌 다른 주제(2025-26: UNEARTHED)로 로봇 미션과 연구 프로젝트를 함께 수행해요.",
            "schedule": [
              { "label": "🗓️ 시즌", "value": "매년 가을~겨울 (한국대회) · 시즌제 운영" },
              { "label": "🌏 글로벌", "value": "한국대회 우승팀 → 글로벌 챔피언십 진출" }
            ],
            "eligibility": [
              "Explore 부문(저연령) / Challenge 부문(만 9세~16세)",
              "팀 단위 참가 (코치·지도자 동반)"
            ],
            "scale": ["세계 100개국+ 수십만 명 참가", "로봇 게임 + 이노베이션 프로젝트 + 핵심가치 종합 평가"],
            "pastWorks": [
              "주제 예시: 쓰레기·해양·에너지·우주 등 매 시즌 사회문제",
              "로봇 미션 + 실생활 문제 해결 연구를 함께 발표"
            ],
            "tips": ["로봇·기계공학·컴공 지망생에게 ==팀워크·엔지니어링·발표 역량==을 한 번에 보여주는 최고의 활동이에요."]
          }
        },
        {
          "name": "WRO 국제로봇올림피아드",
          "org": "WRO KOREA",
          "grades": "초·중·고",
          "url": "https://www.wrokorea.kr/",
          "note": "국가대표 선발 로봇 대회",
          "detail": {
            "summary": "World Robot Olympiad — 전 세계 청소년이 겨루는 국제 로봇 대회의 한국 본선이에요. 한국대회 입상 시 ==국제 결선 진출 자격==이 주어져요.",
            "schedule": [
              { "label": "🗓️ 한국대회", "value": "매년 여름경 (부문별)" },
              { "label": "🌏 2026 국제결선", "value": "인도(아시아)·미국(아메리카)·크로아티아(유럽) 9~10월" }
            ],
            "eligibility": [
              "RoboMission(초·중·고)·Future Innovators·Future Engineers 등 부문별",
              "팀 단위 참가"
            ],
            "scale": ["전 세계 90개국+ 참가", "초·중·고·대학 부문 + AIR SPORTS(드론) 부문"],
            "pastWorks": ["미션 수행 자율 로봇 제작", "Future Innovators: 사회문제 해결 로봇 프로젝트 발표"],
            "tips": ["==초등부부터 단계적==으로 도전할 수 있어 장기 로드맵을 짜기 좋아요."]
          }
        },
        {
          "name": "RoboCup Junior 한국대회",
          "org": "한국로보컵협회",
          "grades": "초·중·고",
          "url": "https://robocupkorea.org",
          "note": "AI·자율로봇 국제 무대",
          "detail": {
            "summary": "AI·자율 로봇 기술 증진을 위한 국제 대회 RoboCup의 청소년 부문이에요. 상위팀은 ==아시아퍼시픽·유럽 챔피언십 출전 자격==을 얻어요.",
            "schedule": [
              { "label": "🗓️ 한국대회", "value": "공식 홈페이지 일정 확인" },
              { "label": "🌏 국제", "value": "RoboCup Asia-Pacific·European Championship 연계" }
            ],
            "eligibility": ["초·중·고등학생 팀", "Soccer·Rescue·OnStage(댄스) 부문"],
            "scale": ["전 세계 수십 개국 참가하는 권위 있는 로봇·AI 대회"],
            "pastWorks": ["자율주행 축구 로봇", "재난 구조 시뮬레이션 로봇", "로봇 공연(OnStage)"],
            "tips": ["==자율주행·센서·AI 알고리즘==을 깊게 다뤄 SW·AI 계열에도 강력해요."]
          }
        },
        {
          "name": "Regeneron ISEF (국제과학경진대회)",
          "org": "Society for Science (미국)",
          "grades": "고",
          "url": "https://www.societyforscience.org/isef/",
          "note": "세계 최고 권위 고교 과학대회",
          "detail": {
            "summary": "==세계 최고 권위의 고교 과학·공학 연구 경진대회==예요. 75개국에서 약 1,800명의 결선 진출자가 매년 5월 미국에서 경쟁해요.",
            "schedule": [
              { "label": "🗓️ 국제 본선", "value": "매년 5월경 (미국)" },
              { "label": "📝 진출", "value": "국가별 제휴 예선(한국 포함) 통과 후 본선" }
            ],
            "eligibility": ["고등학생 (만 14~18세 수준)", "개인 또는 소규모 팀 연구 프로젝트"],
            "scale": ["75개국 / 매년 약 1,800명 결선", "총상금 900만 달러+ ($75,000 대상 등)"],
            "pastWorks": [
              "생명과학·환경·로봇·AI·재료 등 전 분야 연구 프로젝트",
              "수상 시 세계 최정상급 대학 진학에 강력한 증거"
            ],
            "tips": ["==장기 연구(R&E)와 연결==해 1~2년 깊이 있는 프로젝트로 도전하는 것이 정석이에요."]
          }
        },
        {
          "name": "NASA 스페이스앱 챌린지",
          "org": "NASA",
          "grades": "전연령",
          "url": "https://www.spaceappschallenge.org/",
          "note": "세계 최대 글로벌 해커톤",
          "detail": {
            "summary": "NASA와 14개 우주기관이 주최하는 ==세계 최대 규모의 글로벌 해커톤==이에요. NASA 오픈데이터로 우주·지구 문제를 48시간 안에 해결해요. 서울에서도 동시 개최돼요.",
            "schedule": [
              { "label": "🗓️ 2025 개최", "value": "10월 4일~5일 (2일간, 전 세계 동시)" },
              { "label": "📍 서울 행사", "value": "spaceappschallenge.org에서 Seoul 로컬 이벤트 신청" }
            ],
            "eligibility": ["코더·과학자·디자이너·기획자 누구나", "팀 단위 참가 (학생 참여 환영)"],
            "scale": ["167개국 551개 로컬 이벤트 (2025 기준)", "글로벌 위너 선정"],
            "pastWorks": ["NASA 위성 데이터 시각화 앱", "기후·재난 예측 도구", "우주 탐사 교육 콘텐츠"],
            "tips": ["==48시간 협업 개발 경험==은 SW·AI·우주항공 자소서에서 매우 인상적인 소재예요."]
          }
        },
        {
          "name": "Conrad Challenge (국제 혁신·창업)",
          "org": "Conrad Foundation (미국)",
          "grades": "만 13~18세",
          "url": "https://www.conradchallenge.org/",
          "note": "국제 청소년 혁신·창업 대회",
          "detail": {
            "summary": "NASA·휴스턴대 연계로 시작된 ==국제 청소년 혁신·창업 대회==예요. 글로벌 난제를 해결하는 제품·사업 아이디어를 겨뤄요.",
            "schedule": [
              { "label": "🗓️ 운영", "value": "가을~봄 (온라인 단계별 진행)" },
              { "label": "🏁 결선", "value": "Innovation Summit (미국)" }
            ],
            "eligibility": ["만 13~18세", "2~5명 팀 + 성인 멘토 1명 필수"],
            "scale": ["분야: 항공우주·사이버보안·에너지환경·헬스영양 등", "전 세계 참가 / 영어 진행"],
            "pastWorks": ["사회문제 해결형 스타트업 아이디어 + 사업계획서", "시제품·프로토타입 제작"],
            "tips": ["==창업·공학·경영 융합 역량==을 국제 무대에서 검증받는 드문 기회예요."]
          }
        },
        {
          "name": "Technovation Girls",
          "org": "Technovation (미국)",
          "grades": "여학생 만 8~18세",
          "url": "https://technovationchallenge.org/",
          "note": "여학생 AI·앱 개발 국제대회",
          "detail": {
            "summary": "==여학생 대상 세계 최대 AI·앱 개발 교육 프로그램==이에요. 지역사회 문제를 직접 만든 앱·AI로 해결하고 글로벌 무대에서 발표해요.",
            "schedule": [
              { "label": "🗓️ 시즌", "value": "매년 초~여름 (약 12주 과정)" },
              { "label": "🏁 결선", "value": "World Summit" }
            ],
            "eligibility": ["여학생 (만 8~18세)", "팀 단위 + 멘토 지원"],
            "scale": ["전 세계 100개국+ 참가", "앱·AI 프로토타입 + 사업계획 평가"],
            "pastWorks": ["지역 환경·교육·건강 문제 해결 앱", "AI 기반 사회문제 솔루션"],
            "tips": ["==SW·AI·창업 지망 여학생==에게 강력 추천. 코딩 경험이 없어도 멘토와 함께 시작할 수 있어요."]
          }
        }
      ]
    }
  ]
}
