{
  "totalStars": 8,
  "totalJobs": 25,
  "jobsByStarId": {
    "explore": ["doctor", "ai-researcher", "pharmacist"],
    "create": ["ux-designer", "webtoon-artist", "architect", "film-director"],
    "tech": ["fullstack-developer", "game-developer", "cybersecurity-expert"],
    "connect": ["teacher", "social-worker", "marketer"],
    "nature": ["environmental-scientist", "veterinarian", "marine-biologist"],
    "order": ["lawyer", "accountant", "police-detective"],
    "communicate": ["journalist", "pd-director", "announcer"],
    "challenge": ["entrepreneur", "pro-athlete", "space-engineer"]
  },
  "riasecMapping": {
    "R": ["tech", "nature", "challenge"],
    "I": ["explore", "tech", "nature"],
    "A": ["create", "communicate"],
    "S": ["connect", "explore"],
    "E": ["challenge", "order", "communicate"],
    "C": ["order", "tech"]
  },
  "difficultyLevels": {
    "1": "매우 쉬움",
    "2": "쉬움",
    "3": "보통",
    "4": "어려움",
    "5": "매우 어려움"
  },
  "preparationYearsRange": {
    "min": 4,
    "max": 12,
    "average": 7
  },
  "jobFields": {
    "required": ["id", "name", "icon", "shortDesc", "holland", "salaryRange", "futureGrowth", "aiRisk"],
    "optional": ["description", "admissionPath", "entryProcess", "coreCompetencies", "workProcess", "careerTimeline", "admissionStrategy", "dailySchedule"],
    "workProcess": {
      "required": ["title", "description", "phases"],
      "phaseFields": ["id", "phase", "icon", "title", "description", "duration", "tools", "skills", "example"]
    },
    "careerTimeline": {
      "required": ["title", "totalYears", "totalCost", "milestones", "keySuccess"],
      "milestoneFields": ["period", "semester", "icon", "title", "activities", "achievement", "cost", "awards", "subjects", "setak"]
    },
    "dailySchedule": {
      "required": ["title", "basis", "schedule"],
      "scheduleItemFields": ["time", "activity", "icon", "type", "detail"]
    }
  },
  "validationRules": {
    "futureGrowth": {
      "type": "number",
      "min": 1,
      "max": 5
    },
    "aiRisk": {
      "type": "enum",
      "values": ["매우 낮음", "낮음", "중간", "높음", "매우 높음"]
    },
    "holland": {
      "type": "string",
      "pattern": "^[RIASEC](\\+[RIASEC])?$",
      "examples": ["I", "I+S", "R+I", "A+E"]
    }
  }
}
